chip_component/__init__.py
chip_component/example.py
chip_component/frontend/build/asset-manifest.json
chip_component/frontend/build/bootstrap.min.css
chip_component/frontend/build/bootstrap.min.css.map
chip_component/frontend/build/index.html
chip_component/frontend/build/static/css/main.fc2b76fd.css
chip_component/frontend/build/static/css/main.fc2b76fd.css.map
chip_component/frontend/build/static/js/main.9b549df5.js
chip_component/frontend/build/static/js/main.9b549df5.js.LICENSE.txt
chip_component/frontend/build/static/js/main.9b549df5.js.map
streamlit_chip_filter-0.0.19.dist-info/LICENSE
streamlit_chip_filter-0.0.19.dist-info/METADATA
streamlit_chip_filter-0.0.19.dist-info/WHEEL
streamlit_chip_filter-0.0.19.dist-info/top_level.txt
streamlit_chip_filter-0.0.19.dist-info/RECORD
